[
  {
    "channel_name": "a_ma",
    "retrieved_time": "2025-11-17T16:51:06.678376+00:00",
    "new_video_count": 0
  },
  {
    "channel_name": "haha_travel",
    "retrieved_time": "2025-11-17T16:51:10.201441+00:00",
    "new_video_count": 0
  },
  {
    "channel_name": "Laos_SiuChan",
    "retrieved_time": "2025-11-17T16:51:13.601565+00:00",
    "new_video_count": 0
  },
  {
    "channel_name": "Laos_10years",
    "retrieved_time": "2025-11-17T16:51:17.472395+00:00",
    "new_video_count": 0
  },
  {
    "channel_name": "datouxiaotou",
    "retrieved_time": "2025-11-17T16:51:20.288525+00:00",
    "new_video_count": 0
  },
  {
    "channel_name": "cnyifanma",
    "retrieved_time": "2025-11-17T16:51:22.661561+00:00",
    "new_video_count": 0
  },
  {
    "channel_name": "liuweiyuan",
    "retrieved_time": "2025-11-17T16:51:25.127539+00:00",
    "new_video_count": 0
  },
  {
    "channel_name": "zhuoyueqiongyouji",
    "retrieved_time": "2025-11-17T16:51:28.845653+00:00",
    "new_video_count": 0
  },
  {
    "channel_name": "NaJieandYuGuo",
    "retrieved_time": "2025-11-17T16:51:31.731375+00:00",
    "new_video_count": 0
  },
  {
    "channel_name": "ALianYiJiaZaiNongCun",
    "retrieved_time": "2025-11-17T16:51:34.389608+00:00",
    "new_video_count": 0
  },
  {
    "channel_name": "drunkardlee",
    "retrieved_time": "2025-11-17T16:51:37.115492+00:00",
    "new_video_count": 0
  }
]