[
  {
    "channel_name": "a_ma",
    "retrieved_time": "2025-12-02T17:46:42.396948+00:00",
    "new_video_count": 0
  },
  {
    "channel_name": "haha_travel",
    "retrieved_time": "2025-12-02T17:46:46.595355+00:00",
    "new_video_count": 0
  },
  {
    "channel_name": "Laos_SiuChan",
    "retrieved_time": "2025-12-02T17:46:49.018934+00:00",
    "new_video_count": 0
  },
  {
    "channel_name": "Laos_10years",
    "retrieved_time": "2025-12-02T17:46:52.531574+00:00",
    "new_video_count": 0
  },
  {
    "channel_name": "datouxiaotou",
    "retrieved_time": "2025-12-02T17:46:56.266909+00:00",
    "new_video_count": 0
  },
  {
    "channel_name": "cnyifanma",
    "retrieved_time": "2025-12-02T17:46:59.263370+00:00",
    "new_video_count": 0
  },
  {
    "channel_name": "liuweiyuan",
    "retrieved_time": "2025-12-02T17:47:01.591242+00:00",
    "new_video_count": 0
  },
  {
    "channel_name": "zhuoyueqiongyouji",
    "retrieved_time": "2025-12-02T17:47:04.834749+00:00",
    "new_video_count": 0
  },
  {
    "channel_name": "NaJieandYuGuo",
    "retrieved_time": "2025-12-02T17:47:08.889077+00:00",
    "new_video_count": 0
  },
  {
    "channel_name": "ALianYiJiaZaiNongCun",
    "retrieved_time": "2025-12-02T17:47:12.106742+00:00",
    "new_video_count": 0
  },
  {
    "channel_name": "drunkardlee",
    "retrieved_time": "2025-12-02T17:47:16.221047+00:00",
    "new_video_count": 0
  }
]