[
  {
    "channel_name": "a_ma",
    "retrieved_time": "2026-03-12T08:01:14.032302+00:00",
    "new_video_count": 0
  },
  {
    "channel_name": "haha_travel",
    "retrieved_time": "2026-03-12T08:01:17.799583+00:00",
    "new_video_count": 1
  },
  {
    "channel_name": "Laos_SiuChan",
    "retrieved_time": "2026-03-12T08:01:21.782167+00:00",
    "new_video_count": 0
  },
  {
    "channel_name": "Laos_10years",
    "retrieved_time": "2026-03-12T08:01:24.889829+00:00",
    "new_video_count": 1
  },
  {
    "channel_name": "datouxiaotou",
    "retrieved_time": "2026-03-12T08:01:27.648501+00:00",
    "new_video_count": 0
  },
  {
    "channel_name": "cnyifanma",
    "retrieved_time": "2026-03-12T08:01:31.989663+00:00",
    "new_video_count": 1
  },
  {
    "channel_name": "liuweiyuan",
    "retrieved_time": "2026-03-12T08:01:35.919134+00:00",
    "new_video_count": 0
  },
  {
    "channel_name": "zhuoyueqiongyouji",
    "retrieved_time": "2026-03-12T08:01:38.392848+00:00",
    "new_video_count": 1
  },
  {
    "channel_name": "NaJieandYuGuo",
    "retrieved_time": "2026-03-12T08:01:41.270463+00:00",
    "new_video_count": 0
  },
  {
    "channel_name": "ALianYiJiaZaiNongCun",
    "retrieved_time": "2026-03-12T08:01:43.695998+00:00",
    "new_video_count": 0
  },
  {
    "channel_name": "drunkardlee",
    "retrieved_time": "2026-03-12T08:01:47.893650+00:00",
    "new_video_count": 0
  }
]