[
  {
    "channel_name": "a_ma",
    "retrieved_time": "2026-01-25T09:11:00.879468+00:00",
    "new_video_count": 0
  },
  {
    "channel_name": "haha_travel",
    "retrieved_time": "2026-01-25T09:11:05.163188+00:00",
    "new_video_count": 1
  },
  {
    "channel_name": "Laos_SiuChan",
    "retrieved_time": "2026-01-25T09:11:08.322237+00:00",
    "new_video_count": 0
  },
  {
    "channel_name": "Laos_10years",
    "retrieved_time": "2026-01-25T09:11:12.421157+00:00",
    "new_video_count": 1
  },
  {
    "channel_name": "datouxiaotou",
    "retrieved_time": "2026-01-25T09:11:15.588395+00:00",
    "new_video_count": 0
  },
  {
    "channel_name": "cnyifanma",
    "retrieved_time": "2026-01-25T09:11:18.805683+00:00",
    "new_video_count": 1
  },
  {
    "channel_name": "liuweiyuan",
    "retrieved_time": "2026-01-25T09:11:22.435988+00:00",
    "new_video_count": 0
  },
  {
    "channel_name": "zhuoyueqiongyouji",
    "retrieved_time": "2026-01-25T09:11:26.705517+00:00",
    "new_video_count": 1
  },
  {
    "channel_name": "NaJieandYuGuo",
    "retrieved_time": "2026-01-25T09:11:30.353899+00:00",
    "new_video_count": 0
  },
  {
    "channel_name": "ALianYiJiaZaiNongCun",
    "retrieved_time": "2026-01-25T09:11:33.934406+00:00",
    "new_video_count": 0
  },
  {
    "channel_name": "drunkardlee",
    "retrieved_time": "2026-01-25T09:11:37.718115+00:00",
    "new_video_count": 0
  }
]