[
  {
    "channel_name": "a_ma",
    "retrieved_time": "2026-01-15T09:16:42.697592+00:00",
    "new_video_count": 1
  },
  {
    "channel_name": "haha_travel",
    "retrieved_time": "2026-01-15T09:16:46.455344+00:00",
    "new_video_count": 1
  },
  {
    "channel_name": "Laos_SiuChan",
    "retrieved_time": "2026-01-15T09:16:49.770151+00:00",
    "new_video_count": 0
  },
  {
    "channel_name": "Laos_10years",
    "retrieved_time": "2026-01-15T09:16:52.139767+00:00",
    "new_video_count": 1
  },
  {
    "channel_name": "datouxiaotou",
    "retrieved_time": "2026-01-15T09:16:54.679400+00:00",
    "new_video_count": 0
  },
  {
    "channel_name": "cnyifanma",
    "retrieved_time": "2026-01-15T09:16:58.560341+00:00",
    "new_video_count": 1
  },
  {
    "channel_name": "liuweiyuan",
    "retrieved_time": "2026-01-15T09:17:01.438311+00:00",
    "new_video_count": 1
  },
  {
    "channel_name": "zhuoyueqiongyouji",
    "retrieved_time": "2026-01-15T09:17:05.570401+00:00",
    "new_video_count": 0
  },
  {
    "channel_name": "NaJieandYuGuo",
    "retrieved_time": "2026-01-15T09:17:08.463047+00:00",
    "new_video_count": 0
  },
  {
    "channel_name": "ALianYiJiaZaiNongCun",
    "retrieved_time": "2026-01-15T09:17:11.032526+00:00",
    "new_video_count": 0
  },
  {
    "channel_name": "drunkardlee",
    "retrieved_time": "2026-01-15T09:17:14.913834+00:00",
    "new_video_count": 0
  }
]