[
  {
    "channel_name": "a_ma",
    "retrieved_time": "2025-11-28T07:11:00.201231+00:00",
    "new_video_count": 0
  },
  {
    "channel_name": "haha_travel",
    "retrieved_time": "2025-11-28T07:11:02.946016+00:00",
    "new_video_count": 1
  },
  {
    "channel_name": "Laos_SiuChan",
    "retrieved_time": "2025-11-28T07:11:06.805074+00:00",
    "new_video_count": 0
  },
  {
    "channel_name": "Laos_10years",
    "retrieved_time": "2025-11-28T07:11:10.791816+00:00",
    "new_video_count": 1
  },
  {
    "channel_name": "datouxiaotou",
    "retrieved_time": "2025-11-28T07:11:13.254499+00:00",
    "new_video_count": 0
  },
  {
    "channel_name": "cnyifanma",
    "retrieved_time": "2025-11-28T07:11:16.078883+00:00",
    "new_video_count": 1
  },
  {
    "channel_name": "liuweiyuan",
    "retrieved_time": "2025-11-28T07:11:19.582378+00:00",
    "new_video_count": 1
  },
  {
    "channel_name": "zhuoyueqiongyouji",
    "retrieved_time": "2025-11-28T07:11:22.721286+00:00",
    "new_video_count": 0
  },
  {
    "channel_name": "NaJieandYuGuo",
    "retrieved_time": "2025-11-28T07:11:25.958690+00:00",
    "new_video_count": 0
  },
  {
    "channel_name": "ALianYiJiaZaiNongCun",
    "retrieved_time": "2025-11-28T07:11:30.222937+00:00",
    "new_video_count": 0
  },
  {
    "channel_name": "drunkardlee",
    "retrieved_time": "2025-11-28T07:11:33.061187+00:00",
    "new_video_count": 0
  }
]