[
  {
    "channel_name": "a_ma",
    "retrieved_time": "2025-12-29T05:02:57.209742+00:00",
    "new_video_count": 0
  },
  {
    "channel_name": "haha_travel",
    "retrieved_time": "2025-12-29T05:03:00.054288+00:00",
    "new_video_count": 1
  },
  {
    "channel_name": "Laos_SiuChan",
    "retrieved_time": "2025-12-29T05:03:03.098737+00:00",
    "new_video_count": 1
  },
  {
    "channel_name": "Laos_10years",
    "retrieved_time": "2025-12-29T05:03:05.554846+00:00",
    "new_video_count": 1
  },
  {
    "channel_name": "datouxiaotou",
    "retrieved_time": "2025-12-29T05:03:09.322664+00:00",
    "new_video_count": 0
  },
  {
    "channel_name": "cnyifanma",
    "retrieved_time": "2025-12-29T05:03:12.931106+00:00",
    "new_video_count": 0
  },
  {
    "channel_name": "liuweiyuan",
    "retrieved_time": "2025-12-29T05:03:15.672217+00:00",
    "new_video_count": 0
  },
  {
    "channel_name": "zhuoyueqiongyouji",
    "retrieved_time": "2025-12-29T05:03:18.381562+00:00",
    "new_video_count": 0
  },
  {
    "channel_name": "NaJieandYuGuo",
    "retrieved_time": "2025-12-29T05:03:21.708511+00:00",
    "new_video_count": 0
  },
  {
    "channel_name": "ALianYiJiaZaiNongCun",
    "retrieved_time": "2025-12-29T05:03:25.264363+00:00",
    "new_video_count": 0
  },
  {
    "channel_name": "drunkardlee",
    "retrieved_time": "2025-12-29T05:03:28.458325+00:00",
    "new_video_count": 0
  }
]