[
  {
    "channel_name": "a_ma",
    "retrieved_time": "2026-04-19T21:23:36.910209+00:00",
    "new_video_count": 0
  },
  {
    "channel_name": "haha_travel",
    "retrieved_time": "2026-04-19T21:23:39.386991+00:00",
    "new_video_count": 0
  },
  {
    "channel_name": "Laos_SiuChan",
    "retrieved_time": "2026-04-19T21:23:42.737348+00:00",
    "new_video_count": 0
  },
  {
    "channel_name": "Laos_10years",
    "retrieved_time": "2026-04-19T21:23:46.698719+00:00",
    "new_video_count": 0
  },
  {
    "channel_name": "datouxiaotou",
    "retrieved_time": "2026-04-19T21:23:50.603469+00:00",
    "new_video_count": 0
  },
  {
    "channel_name": "cnyifanma",
    "retrieved_time": "2026-04-19T21:23:53.594573+00:00",
    "new_video_count": 0
  },
  {
    "channel_name": "liuweiyuan",
    "retrieved_time": "2026-04-19T21:23:56.763259+00:00",
    "new_video_count": 0
  },
  {
    "channel_name": "zhuoyueqiongyouji",
    "retrieved_time": "2026-04-19T21:23:59.471093+00:00",
    "new_video_count": 0
  },
  {
    "channel_name": "NaJieandYuGuo",
    "retrieved_time": "2026-04-19T21:24:02.109839+00:00",
    "new_video_count": 0
  },
  {
    "channel_name": "ALianYiJiaZaiNongCun",
    "retrieved_time": "2026-04-19T21:24:05.162558+00:00",
    "new_video_count": 0
  },
  {
    "channel_name": "drunkardlee",
    "retrieved_time": "2026-04-19T21:24:07.953110+00:00",
    "new_video_count": 0
  }
]