[
  {
    "channel_name": "a_ma",
    "retrieved_time": "2026-02-09T10:44:29.232657+00:00",
    "new_video_count": 2
  },
  {
    "channel_name": "haha_travel",
    "retrieved_time": "2026-02-09T10:44:32.133406+00:00",
    "new_video_count": 0
  },
  {
    "channel_name": "Laos_SiuChan",
    "retrieved_time": "2026-02-09T10:44:35.226486+00:00",
    "new_video_count": 0
  },
  {
    "channel_name": "Laos_10years",
    "retrieved_time": "2026-02-09T10:44:39.167431+00:00",
    "new_video_count": 1
  },
  {
    "channel_name": "datouxiaotou",
    "retrieved_time": "2026-02-09T10:44:43.171356+00:00",
    "new_video_count": 0
  },
  {
    "channel_name": "cnyifanma",
    "retrieved_time": "2026-02-09T10:44:45.576749+00:00",
    "new_video_count": 1
  },
  {
    "channel_name": "liuweiyuan",
    "retrieved_time": "2026-02-09T10:44:48.722960+00:00",
    "new_video_count": 0
  },
  {
    "channel_name": "zhuoyueqiongyouji",
    "retrieved_time": "2026-02-09T10:44:51.504229+00:00",
    "new_video_count": 1
  },
  {
    "channel_name": "NaJieandYuGuo",
    "retrieved_time": "2026-02-09T10:44:54.258952+00:00",
    "new_video_count": 1
  },
  {
    "channel_name": "ALianYiJiaZaiNongCun",
    "retrieved_time": "2026-02-09T10:44:58.338230+00:00",
    "new_video_count": 0
  },
  {
    "channel_name": "drunkardlee",
    "retrieved_time": "2026-02-09T10:45:01.805022+00:00",
    "new_video_count": 0
  }
]