[
  {
    "channel_name": "a_ma",
    "retrieved_time": "2026-02-14T13:25:48.282941+00:00",
    "new_video_count": 1
  },
  {
    "channel_name": "haha_travel",
    "retrieved_time": "2026-02-14T13:25:52.031571+00:00",
    "new_video_count": 1
  },
  {
    "channel_name": "Laos_SiuChan",
    "retrieved_time": "2026-02-14T13:25:55.645593+00:00",
    "new_video_count": 0
  },
  {
    "channel_name": "Laos_10years",
    "retrieved_time": "2026-02-14T13:25:58.989217+00:00",
    "new_video_count": 1
  },
  {
    "channel_name": "datouxiaotou",
    "retrieved_time": "2026-02-14T13:26:02.306899+00:00",
    "new_video_count": 0
  },
  {
    "channel_name": "cnyifanma",
    "retrieved_time": "2026-02-14T13:26:06.021360+00:00",
    "new_video_count": 0
  },
  {
    "channel_name": "liuweiyuan",
    "retrieved_time": "2026-02-14T13:26:08.735307+00:00",
    "new_video_count": 1
  },
  {
    "channel_name": "zhuoyueqiongyouji",
    "retrieved_time": "2026-02-14T13:26:11.794330+00:00",
    "new_video_count": 0
  },
  {
    "channel_name": "NaJieandYuGuo",
    "retrieved_time": "2026-02-14T13:26:14.432860+00:00",
    "new_video_count": 0
  },
  {
    "channel_name": "ALianYiJiaZaiNongCun",
    "retrieved_time": "2026-02-14T13:26:17.249370+00:00",
    "new_video_count": 1
  },
  {
    "channel_name": "drunkardlee",
    "retrieved_time": "2026-02-14T13:26:20.953093+00:00",
    "new_video_count": 0
  }
]