[
  {
    "channel_name": "a_ma",
    "retrieved_time": "2025-11-22T22:41:01.928923+00:00",
    "new_video_count": 0
  },
  {
    "channel_name": "haha_travel",
    "retrieved_time": "2025-11-22T22:41:05.530537+00:00",
    "new_video_count": 0
  },
  {
    "channel_name": "Laos_SiuChan",
    "retrieved_time": "2025-11-22T22:41:09.215566+00:00",
    "new_video_count": 0
  },
  {
    "channel_name": "Laos_10years",
    "retrieved_time": "2025-11-22T22:41:13.367299+00:00",
    "new_video_count": 0
  },
  {
    "channel_name": "datouxiaotou",
    "retrieved_time": "2025-11-22T22:41:16.375372+00:00",
    "new_video_count": 0
  },
  {
    "channel_name": "cnyifanma",
    "retrieved_time": "2025-11-22T22:41:19.630378+00:00",
    "new_video_count": 0
  },
  {
    "channel_name": "liuweiyuan",
    "retrieved_time": "2025-11-22T22:41:22.879808+00:00",
    "new_video_count": 0
  },
  {
    "channel_name": "zhuoyueqiongyouji",
    "retrieved_time": "2025-11-22T22:41:26.495066+00:00",
    "new_video_count": 0
  },
  {
    "channel_name": "NaJieandYuGuo",
    "retrieved_time": "2025-11-22T22:41:30.688880+00:00",
    "new_video_count": 0
  },
  {
    "channel_name": "ALianYiJiaZaiNongCun",
    "retrieved_time": "2025-11-22T22:41:33.632078+00:00",
    "new_video_count": 0
  },
  {
    "channel_name": "drunkardlee",
    "retrieved_time": "2025-11-22T22:41:37.650974+00:00",
    "new_video_count": 0
  }
]