[
  {
    "channel_name": "a_ma",
    "retrieved_time": "2026-02-20T12:29:40.626366+00:00",
    "new_video_count": 2
  },
  {
    "channel_name": "haha_travel",
    "retrieved_time": "2026-02-20T12:29:44.693717+00:00",
    "new_video_count": 1
  },
  {
    "channel_name": "Laos_SiuChan",
    "retrieved_time": "2026-02-20T12:29:47.942546+00:00",
    "new_video_count": 0
  },
  {
    "channel_name": "Laos_10years",
    "retrieved_time": "2026-02-20T12:29:51.358860+00:00",
    "new_video_count": 2
  },
  {
    "channel_name": "datouxiaotou",
    "retrieved_time": "2026-02-20T12:29:55.233995+00:00",
    "new_video_count": 0
  },
  {
    "channel_name": "cnyifanma",
    "retrieved_time": "2026-02-20T12:29:58.731575+00:00",
    "new_video_count": 1
  },
  {
    "channel_name": "liuweiyuan",
    "retrieved_time": "2026-02-20T12:30:02.537528+00:00",
    "new_video_count": 0
  },
  {
    "channel_name": "zhuoyueqiongyouji",
    "retrieved_time": "2026-02-20T12:30:06.582799+00:00",
    "new_video_count": 1
  },
  {
    "channel_name": "NaJieandYuGuo",
    "retrieved_time": "2026-02-20T12:30:10.724346+00:00",
    "new_video_count": 0
  },
  {
    "channel_name": "ALianYiJiaZaiNongCun",
    "retrieved_time": "2026-02-20T12:30:13.446656+00:00",
    "new_video_count": 0
  },
  {
    "channel_name": "drunkardlee",
    "retrieved_time": "2026-02-20T12:30:16.077643+00:00",
    "new_video_count": 0
  }
]