[
  {
    "channel_name": "a_ma",
    "retrieved_time": "2025-12-08T08:53:45.659434+00:00",
    "new_video_count": 1
  },
  {
    "channel_name": "haha_travel",
    "retrieved_time": "2025-12-08T08:53:49.283054+00:00",
    "new_video_count": 1
  },
  {
    "channel_name": "Laos_SiuChan",
    "retrieved_time": "2025-12-08T08:53:52.470217+00:00",
    "new_video_count": 0
  },
  {
    "channel_name": "Laos_10years",
    "retrieved_time": "2025-12-08T08:53:55.509120+00:00",
    "new_video_count": 1
  },
  {
    "channel_name": "datouxiaotou",
    "retrieved_time": "2025-12-08T08:53:57.987166+00:00",
    "new_video_count": 0
  },
  {
    "channel_name": "cnyifanma",
    "retrieved_time": "2025-12-08T08:54:01.422736+00:00",
    "new_video_count": 1
  },
  {
    "channel_name": "liuweiyuan",
    "retrieved_time": "2025-12-08T08:54:04.813865+00:00",
    "new_video_count": 1
  },
  {
    "channel_name": "zhuoyueqiongyouji",
    "retrieved_time": "2025-12-08T08:54:08.790872+00:00",
    "new_video_count": 1
  },
  {
    "channel_name": "NaJieandYuGuo",
    "retrieved_time": "2025-12-08T08:54:12.163436+00:00",
    "new_video_count": 1
  },
  {
    "channel_name": "ALianYiJiaZaiNongCun",
    "retrieved_time": "2025-12-08T08:54:14.511809+00:00",
    "new_video_count": 0
  },
  {
    "channel_name": "drunkardlee",
    "retrieved_time": "2025-12-08T08:54:16.579988+00:00",
    "new_video_count": 0
  }
]