[
  {
    "channel_name": "a_ma",
    "retrieved_time": "2026-04-13T14:26:19.578762+00:00",
    "new_video_count": 0
  },
  {
    "channel_name": "haha_travel",
    "retrieved_time": "2026-04-13T14:26:22.282343+00:00",
    "new_video_count": 1
  },
  {
    "channel_name": "Laos_SiuChan",
    "retrieved_time": "2026-04-13T14:26:25.332274+00:00",
    "new_video_count": 0
  },
  {
    "channel_name": "Laos_10years",
    "retrieved_time": "2026-04-13T14:26:28.443785+00:00",
    "new_video_count": 1
  },
  {
    "channel_name": "datouxiaotou",
    "retrieved_time": "2026-04-13T14:26:32.236131+00:00",
    "new_video_count": 0
  },
  {
    "channel_name": "cnyifanma",
    "retrieved_time": "2026-04-13T14:26:36.052450+00:00",
    "new_video_count": 1
  },
  {
    "channel_name": "liuweiyuan",
    "retrieved_time": "2026-04-13T14:26:38.896724+00:00",
    "new_video_count": 1
  },
  {
    "channel_name": "zhuoyueqiongyouji",
    "retrieved_time": "2026-04-13T14:26:41.750554+00:00",
    "new_video_count": 1
  },
  {
    "channel_name": "NaJieandYuGuo",
    "retrieved_time": "2026-04-13T14:26:44.673330+00:00",
    "new_video_count": 0
  },
  {
    "channel_name": "ALianYiJiaZaiNongCun",
    "retrieved_time": "2026-04-13T14:26:47.993965+00:00",
    "new_video_count": 1
  },
  {
    "channel_name": "drunkardlee",
    "retrieved_time": "2026-04-13T14:26:52.079727+00:00",
    "new_video_count": 0
  }
]