[
  {
    "channel_name": "a_ma",
    "retrieved_time": "2026-01-31T14:50:23.322907+00:00",
    "new_video_count": 2
  },
  {
    "channel_name": "haha_travel",
    "retrieved_time": "2026-01-31T14:50:26.446366+00:00",
    "new_video_count": 1
  },
  {
    "channel_name": "Laos_SiuChan",
    "retrieved_time": "2026-01-31T14:50:29.366328+00:00",
    "new_video_count": 0
  },
  {
    "channel_name": "Laos_10years",
    "retrieved_time": "2026-01-31T14:50:32.956850+00:00",
    "new_video_count": 1
  },
  {
    "channel_name": "datouxiaotou",
    "retrieved_time": "2026-01-31T14:50:36.793356+00:00",
    "new_video_count": 0
  },
  {
    "channel_name": "cnyifanma",
    "retrieved_time": "2026-01-31T14:50:39.321228+00:00",
    "new_video_count": 1
  },
  {
    "channel_name": "liuweiyuan",
    "retrieved_time": "2026-01-31T14:50:42.000948+00:00",
    "new_video_count": 0
  },
  {
    "channel_name": "zhuoyueqiongyouji",
    "retrieved_time": "2026-01-31T14:50:45.538592+00:00",
    "new_video_count": 0
  },
  {
    "channel_name": "NaJieandYuGuo",
    "retrieved_time": "2026-01-31T14:50:48.266788+00:00",
    "new_video_count": 0
  },
  {
    "channel_name": "ALianYiJiaZaiNongCun",
    "retrieved_time": "2026-01-31T14:50:51.422833+00:00",
    "new_video_count": 0
  },
  {
    "channel_name": "drunkardlee",
    "retrieved_time": "2026-01-31T14:50:55.380794+00:00",
    "new_video_count": 0
  }
]