[
  {
    "channel_name": "a_ma",
    "retrieved_time": "2025-11-18T17:10:40.578198+00:00",
    "new_video_count": 0
  },
  {
    "channel_name": "haha_travel",
    "retrieved_time": "2025-11-18T17:10:44.479076+00:00",
    "new_video_count": 0
  },
  {
    "channel_name": "Laos_SiuChan",
    "retrieved_time": "2025-11-18T17:10:48.256596+00:00",
    "new_video_count": 0
  },
  {
    "channel_name": "Laos_10years",
    "retrieved_time": "2025-11-18T17:10:51.920612+00:00",
    "new_video_count": 0
  },
  {
    "channel_name": "datouxiaotou",
    "retrieved_time": "2025-11-18T17:10:54.836061+00:00",
    "new_video_count": 0
  },
  {
    "channel_name": "cnyifanma",
    "retrieved_time": "2025-11-18T17:10:58.037285+00:00",
    "new_video_count": 0
  },
  {
    "channel_name": "liuweiyuan",
    "retrieved_time": "2025-11-18T17:11:01.022433+00:00",
    "new_video_count": 0
  },
  {
    "channel_name": "zhuoyueqiongyouji",
    "retrieved_time": "2025-11-18T17:11:04.376208+00:00",
    "new_video_count": 0
  },
  {
    "channel_name": "NaJieandYuGuo",
    "retrieved_time": "2025-11-18T17:11:08.102174+00:00",
    "new_video_count": 0
  },
  {
    "channel_name": "ALianYiJiaZaiNongCun",
    "retrieved_time": "2025-11-18T17:11:11.206493+00:00",
    "new_video_count": 0
  },
  {
    "channel_name": "drunkardlee",
    "retrieved_time": "2025-11-18T17:11:14.572278+00:00",
    "new_video_count": 0
  }
]