[
  {
    "channel_name": "a_ma",
    "retrieved_time": "2025-12-14T07:39:11.130482+00:00",
    "new_video_count": 1
  },
  {
    "channel_name": "haha_travel",
    "retrieved_time": "2025-12-14T07:39:14.857681+00:00",
    "new_video_count": 1
  },
  {
    "channel_name": "Laos_SiuChan",
    "retrieved_time": "2025-12-14T07:39:17.689937+00:00",
    "new_video_count": 0
  },
  {
    "channel_name": "Laos_10years",
    "retrieved_time": "2025-12-14T07:39:20.542658+00:00",
    "new_video_count": 1
  },
  {
    "channel_name": "datouxiaotou",
    "retrieved_time": "2025-12-14T07:39:23.409110+00:00",
    "new_video_count": 0
  },
  {
    "channel_name": "cnyifanma",
    "retrieved_time": "2025-12-14T07:39:27.504102+00:00",
    "new_video_count": 1
  },
  {
    "channel_name": "liuweiyuan",
    "retrieved_time": "2025-12-14T07:39:31.046747+00:00",
    "new_video_count": 0
  },
  {
    "channel_name": "zhuoyueqiongyouji",
    "retrieved_time": "2025-12-14T07:39:33.751711+00:00",
    "new_video_count": 0
  },
  {
    "channel_name": "NaJieandYuGuo",
    "retrieved_time": "2025-12-14T07:39:36.367988+00:00",
    "new_video_count": 0
  },
  {
    "channel_name": "ALianYiJiaZaiNongCun",
    "retrieved_time": "2025-12-14T07:39:38.865345+00:00",
    "new_video_count": 0
  },
  {
    "channel_name": "drunkardlee",
    "retrieved_time": "2025-12-14T07:39:42.017631+00:00",
    "new_video_count": 0
  }
]