[
  {
    "channel_name": "a_ma",
    "retrieved_time": "2026-03-21T13:57:25.015842+00:00",
    "new_video_count": 2
  },
  {
    "channel_name": "haha_travel",
    "retrieved_time": "2026-03-21T13:57:27.406599+00:00",
    "new_video_count": 1
  },
  {
    "channel_name": "Laos_SiuChan",
    "retrieved_time": "2026-03-21T13:57:31.073809+00:00",
    "new_video_count": 0
  },
  {
    "channel_name": "Laos_10years",
    "retrieved_time": "2026-03-21T13:57:35.118916+00:00",
    "new_video_count": 1
  },
  {
    "channel_name": "datouxiaotou",
    "retrieved_time": "2026-03-21T13:57:38.444988+00:00",
    "new_video_count": 0
  },
  {
    "channel_name": "cnyifanma",
    "retrieved_time": "2026-03-21T13:57:42.494766+00:00",
    "new_video_count": 1
  },
  {
    "channel_name": "liuweiyuan",
    "retrieved_time": "2026-03-21T13:57:44.897888+00:00",
    "new_video_count": 0
  },
  {
    "channel_name": "zhuoyueqiongyouji",
    "retrieved_time": "2026-03-21T13:57:47.976286+00:00",
    "new_video_count": 0
  },
  {
    "channel_name": "NaJieandYuGuo",
    "retrieved_time": "2026-03-21T13:57:51.553418+00:00",
    "new_video_count": 1
  },
  {
    "channel_name": "ALianYiJiaZaiNongCun",
    "retrieved_time": "2026-03-21T13:57:55.738676+00:00",
    "new_video_count": 0
  },
  {
    "channel_name": "drunkardlee",
    "retrieved_time": "2026-03-21T13:57:59.596582+00:00",
    "new_video_count": 0
  }
]