[
  {
    "channel_name": "a_ma",
    "retrieved_time": "2026-02-07T14:24:39.486958+00:00",
    "new_video_count": 2
  },
  {
    "channel_name": "haha_travel",
    "retrieved_time": "2026-02-07T14:24:42.221186+00:00",
    "new_video_count": 1
  },
  {
    "channel_name": "Laos_SiuChan",
    "retrieved_time": "2026-02-07T14:24:45.604203+00:00",
    "new_video_count": 0
  },
  {
    "channel_name": "Laos_10years",
    "retrieved_time": "2026-02-07T14:24:48.880196+00:00",
    "new_video_count": 1
  },
  {
    "channel_name": "datouxiaotou",
    "retrieved_time": "2026-02-07T14:24:51.471219+00:00",
    "new_video_count": 0
  },
  {
    "channel_name": "cnyifanma",
    "retrieved_time": "2026-02-07T14:24:54.870386+00:00",
    "new_video_count": 1
  },
  {
    "channel_name": "liuweiyuan",
    "retrieved_time": "2026-02-07T14:24:58.830610+00:00",
    "new_video_count": 0
  },
  {
    "channel_name": "zhuoyueqiongyouji",
    "retrieved_time": "2026-02-07T14:25:01.558406+00:00",
    "new_video_count": 0
  },
  {
    "channel_name": "NaJieandYuGuo",
    "retrieved_time": "2026-02-07T14:25:04.650380+00:00",
    "new_video_count": 0
  },
  {
    "channel_name": "ALianYiJiaZaiNongCun",
    "retrieved_time": "2026-02-07T14:25:08.243197+00:00",
    "new_video_count": 0
  },
  {
    "channel_name": "drunkardlee",
    "retrieved_time": "2026-02-07T14:25:11.603493+00:00",
    "new_video_count": 1
  }
]